qlapi/__init__.py
qlapi/ql.py
qlapi/ql_config.py
qlapi/ql_dependence.py
qlapi/ql_env.py
qlapi/ql_log.py
qlapi/ql_script.py
qlapi/ql_system.py
qlapi/ql_task.py
qinglongtool-0.1.3.dist-info/LICENSE
qinglongtool-0.1.3.dist-info/METADATA
qinglongtool-0.1.3.dist-info/WHEEL
qinglongtool-0.1.3.dist-info/RECORD
