Metadata-Version: 2.3
Name: qinglongtool
Version: 0.1.3
Summary: A Python API wrapper for QingLong Panel
License: MIT
Author: mumuwj0001@163.com
Requires-Python: >=3.10,<4.0
Classifier: License :: OSI Approved :: MIT License
Classifier: Programming Language :: Python :: 3
Classifier: Programming Language :: Python :: 3.10
Classifier: Programming Language :: Python :: 3.11
Classifier: Programming Language :: Python :: 3.12
Classifier: Programming Language :: Python :: 3.13
Requires-Dist: httpx (>=0.28.1,<0.29.0)
Project-URL: Repository, https://github.com/amumu0022/QingLongTools
